README.rst
setup.cfg
setup.py
temporenc/__init__.py
temporenc/temporenc.py
temporenc.egg-info/PKG-INFO
temporenc.egg-info/SOURCES.txt
temporenc.egg-info/dependency_links.txt
temporenc.egg-info/top_level.txt