Metadata-Version: 1.1
Name: temporenc
Version: 0.1.0
Summary: Python library for the temporenc format
Home-page: https://github.com/wbolster/temporenc-python
Author: Wouter Bolsterlee
Author-email: uws@xs4all.nl
License: BSD
Platform: UNKNOWN
Classifier: Development Status :: 4 - Beta
Classifier: Intended Audience :: Developers
Classifier: License :: OSI Approved :: BSD License
Classifier: Programming Language :: Python
Classifier: Programming Language :: Python :: 2
Classifier: Programming Language :: Python :: 3
Classifier: Topic :: Database
Classifier: Topic :: Database :: Database Engines/Servers
Classifier: Topic :: Software Development :: Libraries
Classifier: Topic :: Software Development :: Libraries :: Python Modules
